{
  "schemaVersion": 1,
  "id": "enhancedlava",
  "version": "1.0.0",
  "name": "Enhanced Lava",
  "description": "Enhanced Lava - A production-grade Minecraft mod generated by Mod Generator",
  "authors": [
    "Mod Generator"
  ],
  "contact": {},
  "license": "MIT",
  "environment": "*",
  "entrypoints": {
    "main": [
      "com.modgen.enhancedlava.EnhancedLava"
    ],
    "client": [
      "com.modgen.enhancedlava.client.EnhancedLavaClient"
    ]
  },
  "depends": {
    "minecraft": "1.21.1",
    "fabricloader": ">=0.16.9",
    "fabric": "*",
    "java": ">=21"
  }
}